alpha_id/__init__.py
alpha_id/alpha_id.py
alpha_id_py-0.0.3.dist-info/LICENSE
alpha_id_py-0.0.3.dist-info/METADATA
alpha_id_py-0.0.3.dist-info/WHEEL
alpha_id_py-0.0.3.dist-info/top_level.txt
alpha_id_py-0.0.3.dist-info/RECORD
